yacv_server/__init__.py
yacv_server/cad.py
yacv_server/frontend/LicensesDialogContent-nmV3ZWHo.js
yacv_server/frontend/LicensesDialogContent-nmV3ZWHo.js.map
yacv_server/frontend/LineMaterial-C-l4Lou8.js
yacv_server/frontend/LineMaterial-C-l4Lou8.js.map
yacv_server/frontend/LineSegments2-B53Zk4lZ.js
yacv_server/frontend/LineSegments2-B53Zk4lZ.js.map
yacv_server/frontend/LineSegmentsGeometry-Do---oa-.js
yacv_server/frontend/LineSegmentsGeometry-Do---oa-.js.map
yacv_server/frontend/ModelViewerWrapper-DeU4WF1h.js
yacv_server/frontend/ModelViewerWrapper-DeU4WF1h.js.map
yacv_server/frontend/PlaygroundDialogContent-BpMNRrbp.js
yacv_server/frontend/PlaygroundDialogContent-BpMNRrbp.js.map
yacv_server/frontend/Selection-B4RunUou.js
yacv_server/frontend/Selection-B4RunUou.js.map
yacv_server/frontend/favicon-DkZp2Rhr.ico
yacv_server/frontend/index-E76cnppT.js
yacv_server/frontend/index-E76cnppT.js.map
yacv_server/frontend/index.html
yacv_server/frontend/qwantani_afternoon_1k_hdr-C71c9lSz.jpg
yacv_server/frontend/style-BsssCXJD.css
yacv_server/gltf.py
yacv_server/logo.py
yacv_server/myhttp.py
yacv_server/mylogger.py
yacv_server/plugin.py
yacv_server/pubsub.py
yacv_server/py.typed
yacv_server/rwlock.py
yacv_server/tessellate.py
yacv_server/yacv.py
yacv_server-0.10.11.dist-info/LICENSE
yacv_server-0.10.11.dist-info/METADATA
yacv_server-0.10.11.dist-info/WHEEL
yacv_server-0.10.11.dist-info/RECORD
