Metadata-Version: 2.3
Name: yacv-server
Version: 0.10.11
Summary: Yet Another CAD Viewer (server)
License: MIT
Author: Yeicor
Author-email: 4929005+Yeicor@users.noreply.github.com
Requires-Python: >=3.12,<3.13
Classifier: License :: OSI Approved :: MIT License
Classifier: Programming Language :: Python :: 3
Classifier: Programming Language :: Python :: 3.12
Requires-Dist: build123d (>=0.9,<0.10)
Requires-Dist: pillow (>=10.2,<12.0)
Requires-Dist: poetry-core (==2.2.1)
Requires-Dist: pygltflib (>=1.16.2,<2.0.0)
